sphinx_testing/__init__.py
sphinx_testing/path.py
sphinx_testing/tmpdir.py
sphinx_testing/util.py
sphinx_testing-1.0.1.dist-info/AUTHORS
sphinx_testing-1.0.1.dist-info/LICENSE
sphinx_testing-1.0.1.dist-info/METADATA
sphinx_testing-1.0.1.dist-info/WHEEL
sphinx_testing-1.0.1.dist-info/top_level.txt
sphinx_testing-1.0.1.dist-info/RECORD
